wodev/__init__.py
wodev/__main__.py
wodev/wodev.py
WOdEv-1.0.1.dist-info/LICENSE
WOdEv-1.0.1.dist-info/METADATA
WOdEv-1.0.1.dist-info/WHEEL
WOdEv-1.0.1.dist-info/dependency_links.txt
WOdEv-1.0.1.dist-info/entry_points.txt
WOdEv-1.0.1.dist-info/top_level.txt
WOdEv-1.0.1.dist-info/RECORD
