Metadata-Version: 2.1
Name: WOdEv
Version: 1.0.1
Summary: Week Odd (or) Even
Home-page: https://github.com/MohammadSalek/WOdEv
Author: Mohammad Salek
License: MIT
Platform: UNKNOWN
Classifier: License :: OSI Approved :: MIT License
Classifier: Programming Language :: Python :: 3
Classifier: Programming Language :: Python :: 3.6
Requires-Dist: jdatetime (>=3.6.2)
